{
  "path": "C:/Users/seyeo/Documents/kcaptcha-generator-master/.data/train/0fgc_051406.png",
  "width": 160,
  "height": 60,
  "image_format": "png",
  "bbox": [
    {
      "label": "0",
      "xmin": 39,
      "ymin": 0,
      "xmax": 68,
      "ymax": 59
    },
    {
      "label": "f",
      "xmin": 60,
      "ymin": 0,
      "xmax": 84,
      "ymax": 59
    },
    {
      "label": "g",
      "xmin": 70,
      "ymin": 0,
      "xmax": 110,
      "ymax": 59
    },
    {
      "label": "c",
      "xmin": 91,
      "ymin": 0,
      "xmax": 126,
      "ymax": 59
    }
  ]
}