{
  "path": "C:/Users/seyeo/Documents/kcaptcha-generator-master/.data/train/0h14_048633.png",
  "width": 160,
  "height": 60,
  "image_format": "png",
  "bbox": [
    {
      "label": "0",
      "xmin": 36,
      "ymin": 0,
      "xmax": 70,
      "ymax": 59
    },
    {
      "label": "h",
      "xmin": 51,
      "ymin": 0,
      "xmax": 91,
      "ymax": 59
    },
    {
      "label": "1",
      "xmin": 79,
      "ymin": 0,
      "xmax": 102,
      "ymax": 59
    },
    {
      "label": "4",
      "xmin": 93,
      "ymin": 0,
      "xmax": 128,
      "ymax": 59
    }
  ]
}