{
  "path": "C:/Users/seyeo/Documents/kcaptcha-generator-master/.data/train/0k11_024546.png",
  "width": 160,
  "height": 60,
  "image_format": "png",
  "bbox": [
    {
      "label": "0",
      "xmin": 41,
      "ymin": 0,
      "xmax": 71,
      "ymax": 59
    },
    {
      "label": "k",
      "xmin": 58,
      "ymin": 0,
      "xmax": 92,
      "ymax": 59
    },
    {
      "label": "1",
      "xmin": 77,
      "ymin": 0,
      "xmax": 112,
      "ymax": 59
    },
    {
      "label": "1",
      "xmin": 88,
      "ymin": 0,
      "xmax": 126,
      "ymax": 59
    }
  ]
}