{
  "path": "C:/Users/seyeo/Documents/kcaptcha-generator-master/.data/train/1dg9_006578.png",
  "width": 160,
  "height": 60,
  "image_format": "png",
  "bbox": [
    {
      "label": "1",
      "xmin": 38,
      "ymin": 0,
      "xmax": 62,
      "ymax": 59
    },
    {
      "label": "d",
      "xmin": 47,
      "ymin": 0,
      "xmax": 85,
      "ymax": 59
    },
    {
      "label": "g",
      "xmin": 67,
      "ymin": 0,
      "xmax": 108,
      "ymax": 59
    },
    {
      "label": "9",
      "xmin": 93,
      "ymin": 0,
      "xmax": 124,
      "ymax": 59
    }
  ]
}