{
  "path": "C:/Users/seyeo/Documents/kcaptcha-generator-master/.data/train/215c_002871.png",
  "width": 160,
  "height": 60,
  "image_format": "png",
  "bbox": [
    {
      "label": "2",
      "xmin": 39,
      "ymin": 0,
      "xmax": 65,
      "ymax": 59
    },
    {
      "label": "1",
      "xmin": 54,
      "ymin": 0,
      "xmax": 90,
      "ymax": 59
    },
    {
      "label": "5",
      "xmin": 73,
      "ymin": 0,
      "xmax": 102,
      "ymax": 59
    },
    {
      "label": "c",
      "xmin": 97,
      "ymin": 0,
      "xmax": 117,
      "ymax": 59
    }
  ]
}