{
  "path": "C:/Users/seyeo/Documents/kcaptcha-generator-master/.data/train/4aoq_054714.png",
  "width": 160,
  "height": 60,
  "image_format": "png",
  "bbox": [
    {
      "label": "4",
      "xmin": 34,
      "ymin": 0,
      "xmax": 60,
      "ymax": 59
    },
    {
      "label": "a",
      "xmin": 50,
      "ymin": 0,
      "xmax": 81,
      "ymax": 59
    },
    {
      "label": "o",
      "xmin": 65,
      "ymin": 0,
      "xmax": 106,
      "ymax": 59
    },
    {
      "label": "q",
      "xmin": 95,
      "ymin": 0,
      "xmax": 125,
      "ymax": 59
    }
  ]
}