{
  "path": "C:/Users/seyeo/Documents/kcaptcha-generator-master/.data/train/75wi_059161.png",
  "width": 160,
  "height": 60,
  "image_format": "png",
  "bbox": [
    {
      "label": "7",
      "xmin": 40,
      "ymin": 0,
      "xmax": 61,
      "ymax": 59
    },
    {
      "label": "5",
      "xmin": 52,
      "ymin": 0,
      "xmax": 75,
      "ymax": 59
    },
    {
      "label": "w",
      "xmin": 66,
      "ymin": 0,
      "xmax": 111,
      "ymax": 59
    },
    {
      "label": "i",
      "xmin": 103,
      "ymin": 0,
      "xmax": 117,
      "ymax": 59
    }
  ]
}