{
  "path": "C:/Users/seyeo/Documents/kcaptcha-generator-master/.data/train/7die_008890.png",
  "width": 160,
  "height": 60,
  "image_format": "png",
  "bbox": [
    {
      "label": "7",
      "xmin": 37,
      "ymin": 0,
      "xmax": 75,
      "ymax": 59
    },
    {
      "label": "d",
      "xmin": 50,
      "ymin": 0,
      "xmax": 91,
      "ymax": 59
    },
    {
      "label": "i",
      "xmin": 80,
      "ymin": 0,
      "xmax": 98,
      "ymax": 59
    },
    {
      "label": "e",
      "xmin": 89,
      "ymin": 0,
      "xmax": 117,
      "ymax": 59
    }
  ]
}