{
  "path": "C:/Users/seyeo/Documents/kcaptcha-generator-master/.data/train/a5ne_002894.png",
  "width": 160,
  "height": 60,
  "image_format": "png",
  "bbox": [
    {
      "label": "a",
      "xmin": 36,
      "ymin": 0,
      "xmax": 58,
      "ymax": 59
    },
    {
      "label": "5",
      "xmin": 50,
      "ymin": 0,
      "xmax": 81,
      "ymax": 59
    },
    {
      "label": "n",
      "xmin": 73,
      "ymin": 0,
      "xmax": 105,
      "ymax": 59
    },
    {
      "label": "e",
      "xmin": 100,
      "ymin": 0,
      "xmax": 119,
      "ymax": 59
    }
  ]
}