{
  "path": "C:/Users/seyeo/Documents/kcaptcha-generator-master/.data/train/alrn_010945.png",
  "width": 160,
  "height": 60,
  "image_format": "png",
  "bbox": [
    {
      "label": "a",
      "xmin": 38,
      "ymin": 0,
      "xmax": 69,
      "ymax": 59
    },
    {
      "label": "l",
      "xmin": 58,
      "ymin": 0,
      "xmax": 78,
      "ymax": 59
    },
    {
      "label": "r",
      "xmin": 67,
      "ymin": 0,
      "xmax": 90,
      "ymax": 59
    },
    {
      "label": "n",
      "xmin": 81,
      "ymin": 0,
      "xmax": 126,
      "ymax": 59
    }
  ]
}