{
  "path": "C:/Users/seyeo/Documents/kcaptcha-generator-master/.data/train/b2jl_015922.png",
  "width": 160,
  "height": 60,
  "image_format": "png",
  "bbox": [
    {
      "label": "b",
      "xmin": 48,
      "ymin": 0,
      "xmax": 72,
      "ymax": 59
    },
    {
      "label": "2",
      "xmin": 66,
      "ymin": 0,
      "xmax": 89,
      "ymax": 59
    },
    {
      "label": "j",
      "xmin": 77,
      "ymin": 0,
      "xmax": 95,
      "ymax": 59
    },
    {
      "label": "l",
      "xmin": 88,
      "ymin": 0,
      "xmax": 114,
      "ymax": 59
    }
  ]
}