{
  "path": "C:/Users/seyeo/Documents/kcaptcha-generator-master/.data/train/cgph_048020.png",
  "width": 160,
  "height": 60,
  "image_format": "png",
  "bbox": [
    {
      "label": "c",
      "xmin": 37,
      "ymin": 0,
      "xmax": 57,
      "ymax": 59
    },
    {
      "label": "g",
      "xmin": 52,
      "ymin": 0,
      "xmax": 84,
      "ymax": 59
    },
    {
      "label": "p",
      "xmin": 67,
      "ymin": 0,
      "xmax": 102,
      "ymax": 59
    },
    {
      "label": "h",
      "xmin": 96,
      "ymin": 0,
      "xmax": 121,
      "ymax": 59
    }
  ]
}