{
  "path": "C:/Users/seyeo/Documents/kcaptcha-generator-master/.data/train/d1hp_061007.png",
  "width": 160,
  "height": 60,
  "image_format": "png",
  "bbox": [
    {
      "label": "d",
      "xmin": 37,
      "ymin": 0,
      "xmax": 64,
      "ymax": 59
    },
    {
      "label": "1",
      "xmin": 56,
      "ymin": 0,
      "xmax": 73,
      "ymax": 59
    },
    {
      "label": "h",
      "xmin": 64,
      "ymin": 0,
      "xmax": 102,
      "ymax": 59
    },
    {
      "label": "p",
      "xmin": 89,
      "ymin": 0,
      "xmax": 120,
      "ymax": 59
    }
  ]
}