{
  "path": "C:/Users/seyeo/Documents/kcaptcha-generator-master/.data/train/d908_004493.png",
  "width": 160,
  "height": 60,
  "image_format": "png",
  "bbox": [
    {
      "label": "d",
      "xmin": 33,
      "ymin": 0,
      "xmax": 69,
      "ymax": 59
    },
    {
      "label": "9",
      "xmin": 50,
      "ymin": 0,
      "xmax": 90,
      "ymax": 59
    },
    {
      "label": "0",
      "xmin": 76,
      "ymin": 0,
      "xmax": 105,
      "ymax": 59
    },
    {
      "label": "8",
      "xmin": 96,
      "ymin": 0,
      "xmax": 128,
      "ymax": 59
    }
  ]
}