{
  "path": "C:/Users/seyeo/Documents/kcaptcha-generator-master/.data/train/ft2y_016320.png",
  "width": 160,
  "height": 60,
  "image_format": "png",
  "bbox": [
    {
      "label": "f",
      "xmin": 43,
      "ymin": 0,
      "xmax": 70,
      "ymax": 59
    },
    {
      "label": "t",
      "xmin": 50,
      "ymin": 0,
      "xmax": 76,
      "ymax": 59
    },
    {
      "label": "2",
      "xmin": 63,
      "ymin": 0,
      "xmax": 97,
      "ymax": 59
    },
    {
      "label": "y",
      "xmin": 84,
      "ymin": 0,
      "xmax": 113,
      "ymax": 59
    }
  ]
}