{
  "path": "C:/Users/seyeo/Documents/kcaptcha-generator-master/.data/train/gjnz_017651.png",
  "width": 160,
  "height": 60,
  "image_format": "png",
  "bbox": [
    {
      "label": "g",
      "xmin": 35,
      "ymin": 0,
      "xmax": 69,
      "ymax": 59
    },
    {
      "label": "j",
      "xmin": 54,
      "ymin": 0,
      "xmax": 81,
      "ymax": 59
    },
    {
      "label": "n",
      "xmin": 69,
      "ymin": 0,
      "xmax": 101,
      "ymax": 59
    },
    {
      "label": "z",
      "xmin": 92,
      "ymin": 0,
      "xmax": 128,
      "ymax": 59
    }
  ]
}