{
  "path": "C:/Users/seyeo/Documents/kcaptcha-generator-master/.data/train/h0q1_039211.png",
  "width": 160,
  "height": 60,
  "image_format": "png",
  "bbox": [
    {
      "label": "h",
      "xmin": 34,
      "ymin": 0,
      "xmax": 66,
      "ymax": 59
    },
    {
      "label": "0",
      "xmin": 54,
      "ymin": 0,
      "xmax": 89,
      "ymax": 59
    },
    {
      "label": "q",
      "xmin": 72,
      "ymin": 0,
      "xmax": 115,
      "ymax": 59
    },
    {
      "label": "1",
      "xmin": 100,
      "ymin": 0,
      "xmax": 127,
      "ymax": 59
    }
  ]
}