{
  "path": "C:/Users/seyeo/Documents/kcaptcha-generator-master/.data/train/i255_006632.png",
  "width": 160,
  "height": 60,
  "image_format": "png",
  "bbox": [
    {
      "label": "i",
      "xmin": 42,
      "ymin": 0,
      "xmax": 56,
      "ymax": 59
    },
    {
      "label": "2",
      "xmin": 51,
      "ymin": 0,
      "xmax": 84,
      "ymax": 59
    },
    {
      "label": "5",
      "xmin": 68,
      "ymin": 0,
      "xmax": 95,
      "ymax": 59
    },
    {
      "label": "5",
      "xmin": 90,
      "ymin": 0,
      "xmax": 109,
      "ymax": 59
    }
  ]
}