{
  "path": "C:/Users/seyeo/Documents/kcaptcha-generator-master/.data/train/i4e5_036652.png",
  "width": 160,
  "height": 60,
  "image_format": "png",
  "bbox": [
    {
      "label": "i",
      "xmin": 45,
      "ymin": 0,
      "xmax": 61,
      "ymax": 59
    },
    {
      "label": "4",
      "xmin": 55,
      "ymin": 0,
      "xmax": 78,
      "ymax": 59
    },
    {
      "label": "e",
      "xmin": 70,
      "ymin": 0,
      "xmax": 101,
      "ymax": 59
    },
    {
      "label": "5",
      "xmin": 85,
      "ymin": 0,
      "xmax": 116,
      "ymax": 59
    }
  ]
}