{
  "path": "C:/Users/seyeo/Documents/kcaptcha-generator-master/.data/train/ku49_021055.png",
  "width": 160,
  "height": 60,
  "image_format": "png",
  "bbox": [
    {
      "label": "k",
      "xmin": 36,
      "ymin": 0,
      "xmax": 65,
      "ymax": 59
    },
    {
      "label": "u",
      "xmin": 56,
      "ymin": 0,
      "xmax": 94,
      "ymax": 59
    },
    {
      "label": "4",
      "xmin": 75,
      "ymin": 0,
      "xmax": 111,
      "ymax": 59
    },
    {
      "label": "9",
      "xmin": 99,
      "ymin": 0,
      "xmax": 123,
      "ymax": 59
    }
  ]
}