{
  "path": "C:/Users/seyeo/Documents/kcaptcha-generator-master/.data/train/lo3f_018187.png",
  "width": 160,
  "height": 60,
  "image_format": "png",
  "bbox": [
    {
      "label": "l",
      "xmin": 43,
      "ymin": 0,
      "xmax": 64,
      "ymax": 59
    },
    {
      "label": "o",
      "xmin": 51,
      "ymin": 0,
      "xmax": 82,
      "ymax": 59
    },
    {
      "label": "3",
      "xmin": 68,
      "ymin": 0,
      "xmax": 104,
      "ymax": 59
    },
    {
      "label": "f",
      "xmin": 90,
      "ymin": 0,
      "xmax": 122,
      "ymax": 59
    }
  ]
}