{
  "path": "C:/Users/seyeo/Documents/kcaptcha-generator-master/.data/train/ma1e_030508.png",
  "width": 160,
  "height": 60,
  "image_format": "png",
  "bbox": [
    {
      "label": "m",
      "xmin": 31,
      "ymin": 0,
      "xmax": 76,
      "ymax": 59
    },
    {
      "label": "a",
      "xmin": 65,
      "ymin": 0,
      "xmax": 96,
      "ymax": 59
    },
    {
      "label": "1",
      "xmin": 87,
      "ymin": 0,
      "xmax": 107,
      "ymax": 59
    },
    {
      "label": "e",
      "xmin": 101,
      "ymin": 0,
      "xmax": 124,
      "ymax": 59
    }
  ]
}