{
  "path": "C:/Users/seyeo/Documents/kcaptcha-generator-master/.data/train/mjx7_003230.png",
  "width": 160,
  "height": 60,
  "image_format": "png",
  "bbox": [
    {
      "label": "m",
      "xmin": 34,
      "ymin": 0,
      "xmax": 89,
      "ymax": 59
    },
    {
      "label": "j",
      "xmin": 66,
      "ymin": 0,
      "xmax": 96,
      "ymax": 59
    },
    {
      "label": "x",
      "xmin": 81,
      "ymin": 0,
      "xmax": 114,
      "ymax": 59
    },
    {
      "label": "7",
      "xmin": 98,
      "ymin": 0,
      "xmax": 125,
      "ymax": 59
    }
  ]
}