{
  "path": "C:/Users/seyeo/Documents/kcaptcha-generator-master/.data/train/mqq7_012265.png",
  "width": 160,
  "height": 60,
  "image_format": "png",
  "bbox": [
    {
      "label": "m",
      "xmin": 26,
      "ymin": 0,
      "xmax": 74,
      "ymax": 59
    },
    {
      "label": "q",
      "xmin": 56,
      "ymin": 0,
      "xmax": 97,
      "ymax": 59
    },
    {
      "label": "q",
      "xmin": 85,
      "ymin": 0,
      "xmax": 115,
      "ymax": 59
    },
    {
      "label": "7",
      "xmin": 103,
      "ymin": 0,
      "xmax": 140,
      "ymax": 59
    }
  ]
}