{
  "path": "C:/Users/seyeo/Documents/kcaptcha-generator-master/.data/train/n01a_015633.png",
  "width": 160,
  "height": 60,
  "image_format": "png",
  "bbox": [
    {
      "label": "n",
      "xmin": 35,
      "ymin": 0,
      "xmax": 63,
      "ymax": 59
    },
    {
      "label": "0",
      "xmin": 59,
      "ymin": 0,
      "xmax": 87,
      "ymax": 59
    },
    {
      "label": "1",
      "xmin": 75,
      "ymin": 0,
      "xmax": 108,
      "ymax": 59
    },
    {
      "label": "a",
      "xmin": 103,
      "ymin": 0,
      "xmax": 125,
      "ymax": 59
    }
  ]
}