{
  "path": "C:/Users/seyeo/Documents/kcaptcha-generator-master/.data/train/no5a_017452.png",
  "width": 160,
  "height": 60,
  "image_format": "png",
  "bbox": [
    {
      "label": "n",
      "xmin": 31,
      "ymin": 0,
      "xmax": 67,
      "ymax": 59
    },
    {
      "label": "o",
      "xmin": 57,
      "ymin": 0,
      "xmax": 87,
      "ymax": 59
    },
    {
      "label": "5",
      "xmin": 76,
      "ymin": 0,
      "xmax": 116,
      "ymax": 59
    },
    {
      "label": "a",
      "xmin": 96,
      "ymin": 0,
      "xmax": 133,
      "ymax": 59
    }
  ]
}