{
  "path": "C:/Users/seyeo/Documents/kcaptcha-generator-master/.data/train/rcr3_031266.png",
  "width": 160,
  "height": 60,
  "image_format": "png",
  "bbox": [
    {
      "label": "r",
      "xmin": 41,
      "ymin": 0,
      "xmax": 72,
      "ymax": 59
    },
    {
      "label": "c",
      "xmin": 52,
      "ymin": 0,
      "xmax": 87,
      "ymax": 59
    },
    {
      "label": "r",
      "xmin": 69,
      "ymin": 0,
      "xmax": 98,
      "ymax": 59
    },
    {
      "label": "3",
      "xmin": 89,
      "ymin": 0,
      "xmax": 113,
      "ymax": 59
    }
  ]
}