{
  "path": "C:/Users/seyeo/Documents/kcaptcha-generator-master/.data/train/rumn_017017.png",
  "width": 160,
  "height": 60,
  "image_format": "png",
  "bbox": [
    {
      "label": "r",
      "xmin": 31,
      "ymin": 0,
      "xmax": 56,
      "ymax": 59
    },
    {
      "label": "u",
      "xmin": 38,
      "ymin": 0,
      "xmax": 75,
      "ymax": 59
    },
    {
      "label": "m",
      "xmin": 58,
      "ymin": 0,
      "xmax": 106,
      "ymax": 59
    },
    {
      "label": "n",
      "xmin": 96,
      "ymin": 0,
      "xmax": 131,
      "ymax": 59
    }
  ]
}