{
  "path": "C:/Users/seyeo/Documents/kcaptcha-generator-master/.data/train/shi0_049635.png",
  "width": 160,
  "height": 60,
  "image_format": "png",
  "bbox": [
    {
      "label": "s",
      "xmin": 42,
      "ymin": 0,
      "xmax": 61,
      "ymax": 59
    },
    {
      "label": "h",
      "xmin": 51,
      "ymin": 0,
      "xmax": 90,
      "ymax": 59
    },
    {
      "label": "i",
      "xmin": 78,
      "ymin": 0,
      "xmax": 101,
      "ymax": 59
    },
    {
      "label": "0",
      "xmin": 91,
      "ymin": 0,
      "xmax": 114,
      "ymax": 59
    }
  ]
}