{
  "path": "C:/Users/seyeo/Documents/kcaptcha-generator-master/.data/train/szb8_017955.png",
  "width": 160,
  "height": 60,
  "image_format": "png",
  "bbox": [
    {
      "label": "s",
      "xmin": 39,
      "ymin": 0,
      "xmax": 54,
      "ymax": 59
    },
    {
      "label": "z",
      "xmin": 50,
      "ymin": 0,
      "xmax": 80,
      "ymax": 59
    },
    {
      "label": "b",
      "xmin": 68,
      "ymin": 0,
      "xmax": 99,
      "ymax": 59
    },
    {
      "label": "8",
      "xmin": 97,
      "ymin": 0,
      "xmax": 118,
      "ymax": 59
    }
  ]
}