{
  "path": "C:/Users/seyeo/Documents/kcaptcha-generator-master/.data/train/vjr5_005585.png",
  "width": 160,
  "height": 60,
  "image_format": "png",
  "bbox": [
    {
      "label": "v",
      "xmin": 43,
      "ymin": 0,
      "xmax": 73,
      "ymax": 59
    },
    {
      "label": "j",
      "xmin": 59,
      "ymin": 0,
      "xmax": 79,
      "ymax": 59
    },
    {
      "label": "r",
      "xmin": 69,
      "ymin": 0,
      "xmax": 100,
      "ymax": 59
    },
    {
      "label": "5",
      "xmin": 83,
      "ymin": 0,
      "xmax": 120,
      "ymax": 59
    }
  ]
}