{
  "path": "C:/Users/seyeo/Documents/kcaptcha-generator-master/.data/train/vmzt_029018.png",
  "width": 160,
  "height": 60,
  "image_format": "png",
  "bbox": [
    {
      "label": "v",
      "xmin": 33,
      "ymin": 0,
      "xmax": 62,
      "ymax": 59
    },
    {
      "label": "m",
      "xmin": 50,
      "ymin": 0,
      "xmax": 103,
      "ymax": 59
    },
    {
      "label": "z",
      "xmin": 87,
      "ymin": 0,
      "xmax": 119,
      "ymax": 59
    },
    {
      "label": "t",
      "xmin": 107,
      "ymin": 0,
      "xmax": 126,
      "ymax": 59
    }
  ]
}