{
  "path": "C:/Users/seyeo/Documents/kcaptcha-generator-master/.data/train/vp8z_009370.png",
  "width": 160,
  "height": 60,
  "image_format": "png",
  "bbox": [
    {
      "label": "v",
      "xmin": 32,
      "ymin": 0,
      "xmax": 69,
      "ymax": 59
    },
    {
      "label": "p",
      "xmin": 49,
      "ymin": 0,
      "xmax": 85,
      "ymax": 59
    },
    {
      "label": "8",
      "xmin": 79,
      "ymin": 0,
      "xmax": 103,
      "ymax": 59
    },
    {
      "label": "z",
      "xmin": 94,
      "ymin": 0,
      "xmax": 127,
      "ymax": 59
    }
  ]
}