{
  "path": "C:/Users/seyeo/Documents/kcaptcha-generator-master/.data/train/zhu8_018911.png",
  "width": 160,
  "height": 60,
  "image_format": "png",
  "bbox": [
    {
      "label": "z",
      "xmin": 35,
      "ymin": 0,
      "xmax": 64,
      "ymax": 59
    },
    {
      "label": "h",
      "xmin": 53,
      "ymin": 0,
      "xmax": 84,
      "ymax": 59
    },
    {
      "label": "u",
      "xmin": 68,
      "ymin": 0,
      "xmax": 109,
      "ymax": 59
    },
    {
      "label": "8",
      "xmin": 92,
      "ymin": 0,
      "xmax": 128,
      "ymax": 59
    }
  ]
}